oraclemanager/__init__.py
oraclemanager/oracle_manager.py
oraclemanager-2.0.0.dist-info/LICENSE.txt
oraclemanager-2.0.0.dist-info/METADATA
oraclemanager-2.0.0.dist-info/WHEEL
oraclemanager-2.0.0.dist-info/top_level.txt
oraclemanager-2.0.0.dist-info/RECORD
