Metadata-Version: 2.1
Name: oraclemanager
Version: 2.0.0
Summary: API wrapper around python-oracledb to more easily perform simple database tasks.
Author: Erik Bierbrauer
Project-URL: Homepage, https://github.com/ebier92/oraclemanager
Project-URL: Bug Tracker, https://github.com/ebier92/oraclemanager/issues
Classifier: Programming Language :: Python :: 3
Classifier: License :: OSI Approved :: Apache Software License
Classifier: Operating System :: OS Independent
Requires-Python: >=3.11
License-File: LICENSE.txt
Requires-Dist: oracledb ==2.4.1
